takagi_fact/__init__.py
tests/__init__.py
tests/test.py
takagi_fact-0.4.1.dist-info/LICENSE
takagi_fact-0.4.1.dist-info/METADATA
takagi_fact-0.4.1.dist-info/WHEEL
takagi_fact-0.4.1.dist-info/top_level.txt
takagi_fact-0.4.1.dist-info/RECORD
