Metadata-Version: 2.1
Name: takagi-fact
Version: 0.4.1
Summary: A libary for the symmetric SVD and the Takagi factorization
Home-page: https://github.com/hajifkd/takagi_fact/
Author: Hajime Fukuda
Author-email: hajime.fukuda@me.com
License: UNKNOWN
Platform: UNKNOWN
Classifier: Programming Language :: Python :: 3
Classifier: License :: OSI Approved :: MIT License
Classifier: Topic :: Scientific/Engineering :: Mathematics
Requires-Dist: mpmath
